pip_review/__init__.py
pip_review/__main__.py
pip_review-1.2.0.dist-info/LICENSE.txt
pip_review-1.2.0.dist-info/METADATA
pip_review-1.2.0.dist-info/WHEEL
pip_review-1.2.0.dist-info/entry_points.txt
pip_review-1.2.0.dist-info/top_level.txt
pip_review-1.2.0.dist-info/RECORD
