Metadata-Version: 2.1
Name: pip-review
Version: 1.2.0
Summary: pip-review lets you smoothly manage all available PyPI updates. 
Home-page: https://github.com/jgonggrijp/pip-review
Author: Julian Gonggrijp, Vincent Driessen
Author-email: j.gonggrijp@gmail.com
License: BSD
Platform: any
Classifier: Development Status :: 5 - Production/Stable
Classifier: Programming Language :: Python
Classifier: Programming Language :: Python :: 2
Classifier: Programming Language :: Python :: 2.7
Classifier: Programming Language :: Python :: 3
Classifier: Programming Language :: Python :: 3.3
Classifier: Programming Language :: Python :: 3.4
Classifier: Programming Language :: Python :: 3.5
Classifier: Programming Language :: Python :: 3.6
Classifier: Programming Language :: Python :: 3.7
Classifier: Programming Language :: Python :: 3.8
Classifier: Programming Language :: Python :: 3.9
Classifier: Programming Language :: Python :: 3.10
Classifier: Intended Audience :: Developers
Classifier: Intended Audience :: System Administrators
Classifier: License :: OSI Approved :: BSD License
Classifier: Operating System :: OS Independent
Classifier: Topic :: System :: Systems Administration
Requires-Python: >=2.7, !=3.0, !=3.1, !=3.2
Requires-Dist: packaging
Requires-Dist: pip
